Metadata-Version: 2.1
Name: pystringmatcher
Version: 0.0.9
Summary: A package for matching a set of strings and textual patterns in a given text file
Home-page: https://github.com/aviadtamir/pystringmatcher.git
Author: Aviad Tamir
Author-email: aviadt15@gmail.com
License: MIT license
Platform: UNKNOWN
Classifier: Programming Language :: Python :: 3.7
Classifier: Programming Language :: Python :: 3.8
Requires-Python: >=3.7
Requires-Dist: cached-property
Requires-Dist: vcversioner
